README.md
lock.py
setup.py
lock.egg-info/PKG-INFO
lock.egg-info/SOURCES.txt
lock.egg-info/dependency_links.txt
lock.egg-info/entry_points.txt
lock.egg-info/top_level.txt