Metadata-Version: 1.0
Name: lock
Version: 2018.3.25.2110
Summary: module for enabling file locks
Home-page: https://github.com/wdbm/lock
Author: Will Breaden Madden
Author-email: wbm@protonmail.ch
License: GPLv3
Platform: UNKNOWN
